Workbook

Sheet Cover
E2: SYSTEM TEST CASE
B4: Project Name | C4: <Project Name> | F4: Creator
B5: Project Code | C5: <Project Code> | F5: Reviewer/Approver
B6: Document Code | C6: =C5&"_"&"XXX"&"_"&"vx.x" -> <Project Code>_XXX_vx.x | F6: Issue Date
F7: Version
B10: Record of change
B11: Effective Date | C11: Version | D11: Change Item | E11: *A,D,M | F11: Change description | G11: Reference
B12: <Date when these changes are effective> | G12: <List of documents which are referred in this version.>

Sheet Feature1
A2: Feature | B2: <Feature Name1> | M2: Pass
A3: Test requirement | B3: <Brief description about requirements which are tested in this sheet> | M3: Fail
A4: Reference Document | M4: Untesed
A5: Pass | B5: Fail | C5: Untested | D5: N/A | F5: Number of Test cases | M5: N/A
A6: =COUNTIF(H10:H998,"Pass") -> 0 | B6: =COUNTIF(H10:H998,"Fail") -> 0 | C6: =F6-D6-B6-A6 -> 8 | D6: =COUNTIF(H10:H998,"N/A") -> 0 | F6: =COUNTA(A10:A998) -> 8
A8: ID | B8: Test Case Description | C8: Test Case Procedure | D8: Expected Results | E8: Actual Results | F8: Inter-test case Dependence | G8: Result | H8: Test date | I8: Tester | J8: Note
A9: Login (each function includes multiple test cases to check User Interface (GUI), Data Validation (GUI), Functionality, Non-Functionality,..)
A10: Login - 1 | B10: Kiểm thử đăng nhập thành công | C10: 1. Truy cập vào website 2. Click vào nút login. 3. Điển username: huonglh 4. Điền password: 123 5. Click nút sign… | D10: 1. Nhận được thông báo "đăng nhập thành công" 2. Được chuyển sang trang chủ. | E10: 1. Nhận được thông báo "đăng nhập thành công" 2. Được chuyển sang trang chủ. | F10: - Tài khoản phải tồn tại và không bị deactive | G10: Pass
A11: Login - 2 | B11: <Test case 2>
A12: Login -3 | B12: <Test case 3>
A13: Function B (each function includes multiple test cases to check User Interface (GUI), Data Validation (GUI), Functionality, Non-Functionality,..)
A14: =IF(OR(B14<>"",D14<>""),"["&TEXT($B$2,"##")&"-"&TEXT(ROW()-11,"##")&"]","") -> [<Feature Name1>-3] | B14: <Test case 4>
A15: =IF(OR(B15<>"",D15<>""),"["&TEXT($B$2,"##")&"-"&TEXT(ROW()-11,"##")&"]","") -> [<Feature Name1>-4] | B15: <Test case 5>
A16: Function C (each function includes multiple test cases to check User Interface (GUI), Data Validation (GUI), Functionality, Non-Functionality,..)
A17: =IF(OR(B17<>"",D17<>""),"["&TEXT($B$2,"##")&"-"&TEXT(ROW()-12,"##")&"]","") -> [<Feature Name1>-5] | B17: <Test case 6>

Sheet Feature2
A2: Feature | B2: <Feature Name2> | L2: Pass
A3: Test requirement | B3: <Brief description about requirements which are tested in this sheet> | L3: Fail
A4: Reference Document | L4: Untesed
A5: Pass | B5: Fail | C5: Untested | D5: N/A | E5: Number of Test cases | L5: N/A
A6: =COUNTIF(G10:G998,"Pass") -> 0 | B6: =COUNTIF(G10:G998,"Fail") -> 0 | C6: =E6-D6-B6-A6 -> 8 | D6: =COUNTIF(G10:G998,"N/A") -> 0 | E6: =COUNTA(A10:A998) -> 8
A8: ID | B8: Test Case Description | C8: Test Case Procedure | D8: Expected Results | E8: Inter-test case Dependence | F8: Result | G8: Test date | H8: Tester | I8: Note
A9: Function A (each function includes multiple test cases to check User Interface (GUI), Data Validation (GUI), Functionality, Non-Functionality,..)
A10: =IF(OR(B10<>"",D10<>""),"["&TEXT($B$2,"##")&"-"&TEXT(ROW()-10,"##")&"]","") -> [<Feature Name2>-] | B10: <Brief description of this case: what is tested?> Ex: Test viewing "Company" form. | C10: <Describe steps to perform this case> Ex: 1. Login the system with Manager role. 2. Click "Company" tab in the left menu. | D10: <Describe results which meet customer's requirement> Ex: The "Company" view form is displayed with the folowing informations: - Company name - Company address - Phone - Fax | E10: <List all test cases or conditions that must be done before performing this case> | F10: Pass
A11: =IF(OR(B11<>"",D11<>""),"["&TEXT($B$2,"##")&"-"&TEXT(ROW()-10,"##")&"]","") -> [<Feature Name2>-1] | B11: <Test case 2>
A12: =IF(OR(B12<>"",D12<>""),"["&TEXT($B$2,"##")&"-"&TEXT(ROW()-10,"##")&"]","") -> [<Feature Name2>-2] | B12: <Test case 3>
A13: Function B (each function includes multiple test cases to check User Interface (GUI), Data Validation (GUI), Functionality, Non-Functionality,..)
A14: =IF(OR(B14<>"",D14<>""),"["&TEXT($B$2,"##")&"-"&TEXT(ROW()-11,"##")&"]","") -> [<Feature Name2>-3] | B14: <Test case 4>
A15: =IF(OR(B15<>"",D15<>""),"["&TEXT($B$2,"##")&"-"&TEXT(ROW()-11,"##")&"]","") -> [<Feature Name2>-4] | B15: <Test case 5>
A16: Function C (each function includes multiple test cases to check User Interface (GUI), Data Validation (GUI), Functionality, Non-Functionality,..)
A17: =IF(OR(B17<>"",D17<>""),"["&TEXT($B$2,"##")&"-"&TEXT(ROW()-12,"##")&"]","") -> [<Feature Name2>-5] | B17: <Test case 6>

Sheet Test Report
B1: TEST REPORT
B3: Project Name | C3: <Project Name> | E3: Creator
B4: Project Code | C4: <Project Code> | E4: Reviewer/Approver
B5: Document Code | C5: =C4&"_"&"Test Report"&"_"&"vx.x" -> <Project Code>_Test Report_vx.x | E5: Issue Date | H5: <Date when this test report is created>
B6: Notes | C6: <List modules included in this release> ex: Release 1 includes 2 modules: Module1 and Module2
B10: No | C10: Module code | D10: Pass | E10: Fail | F10: Untested | G10: N/A | H10: Number of test cases
B11: 1 | C11: =Feature1!B2 -> <Feature Name1> | D11: =Feature1!A6 -> 0 | E11: =Feature1!B6 -> 0 | F11: =Feature1!C6 -> 8 | G11: =Feature1!D6 -> 0 | H11: =Feature1!F6 -> 8
B12: 2 | C12: =Feature2!B2 -> <Feature Name2> | D12: =Feature2!A6 -> 0 | E12: =Feature2!B6 -> 0 | F12: =Feature2!C6 -> 8 | G12: =Feature2!D6 -> 0 | H12: =Feature2!E6 -> 8
C14: Sub total | D14: =SUM(D9:D13) -> 0 | E14: =SUM(E9:E13) -> 0 | F14: =SUM(F9:F13) -> 16 | G14: =SUM(G9:G13) -> 0 | H14: =SUM(H9:H13) -> 16
C16: Test coverage | E16: =(D14+E14)*100/(H14-G14) -> 0 | F16: %
C17: Test successful coverage | E17: =D14*100/(H14-G14) -> 0 | F17: %

Sheet FunctionList
A1: No | B1: Requirement Name | C1: Class Name | D1: Function Name | E1: Function Code(Optional) | F1: Sheet Name | G1: Description | H1: Pre-Condition
A2: 1 | B2: FeeController | C2: View Fee Types List | D2: GetFeeTypes | F2: View Fee Types List | G2: Retrieves a list of all fee types configured in the system. | H2: User is authenticated.
A3: 2 | B3: FeeController | C3: Add New Fee Type | D3: CreateFeeType | F3: Add New Fee Type | G3: Creates a new fee type with specific pricing rules. | H3: User has admin or accountant privileges.
A4: 3 | B4: FeeController | C4: Update Fee Type Information | D4: UpdateFeeType | F4: Update Fee Type | G4: Updates the details of an existing fee type. | H4: The selected fee type exists in the system.
A5: 4 | B5: FeeController | C5: Delete Fee Type | D5: DeleteFeeType | F5: Delete Fee Type | G5: Removes a fee type from the system. | H5: The fee type is not currently in use by any invoice.
A6: 5 | B6: UtilityController | C6: View Current Utility Rates | D6: GetUtilityRates | F6: View Utility Rates | G6: Displays the current unit prices for utilities (electricity, water). | H6: User is authenticated.
A7: 6 | B7: UtilityController | C7: Setup New Utility Tiers | D7: CreateUtilityTier | F7: Setup Utility Tiers | G7: Sets up new pricing tiers for utility consumption. | H7: User has admin privileges.
A8: 7 | B8: UtilityController | C8: DeleteTier Unit Prices | D8: DeleteUtilityTier | F8: Delete Utility Tier | G8: Deletes a specific utility pricing tier. | H8: The tier exists and is not actively billing.
A9: 8 | B9: ConfigurationController | C9: View current fee configuration | D9: GetFeeConfig | F9: View Fee Config | G9: Retrieves the current global fee configurations. | H9: User is authenticated.
A10: 9 | B10: ConfigurationController | C10: Set configuration | D10: UpdateFeeConfig | F10: Set Config | G10: Updates the global fee settings. | H10: User has admin privileges.
A11: 10 | B11: InvoiceController | C11: View Invoice List | D11: GetInvoices | F11: View Invoice List | G11: Displays a list of all invoices with their current status. | H11: User is authenticated.
A12: 11 | B12: InvoiceController | C12: View Invoice Details | D12: GetInvoiceById | F12: View Invoice Details | G12: Shows detailed information, line items, and history of a specific invoice. | H12: The invoice exists in the system.
A13: 12 | B13: InvoiceController | C13: Refund Invoice | D13: RefundInvoice | F13: Refund Invoice | G13: Processes a refund for a paid invoice. | H13: The invoice is fully paid and eligible for refund.
... A48: 47 | B48: NotificationController | C48: Delete notification | D48: DeleteNotification | F48: Delete Notification | G48: Removes a notification from the panel. | H48: The notification exists.
